sppr/__init__.py
sppr/app.py
sppr-1.0.0.dist-info/METADATA
sppr-1.0.0.dist-info/WHEEL
sppr-1.0.0.dist-info/top_level.txt
sppr-1.0.0.dist-info/RECORD
